hmfast/__init__.py
hmfast/emulator.py
hmfast/halo_model.py
hmfast/utils.py
hmfast-0.1.0.dist-info/licenses/LICENSE
hmfast-0.1.0.dist-info/METADATA
hmfast-0.1.0.dist-info/WHEEL
hmfast-0.1.0.dist-info/top_level.txt
hmfast-0.1.0.dist-info/RECORD
