Metadata-Version: 2.4
Name: hmfast
Version: 0.1.0
Summary: Machine learning accelerated and differentiable halo model code
Author-email: Boris <boris@example.com>
License:                                  Apache License
Project-URL: Homepage, https://github.com/class_sz_organization/hmfast
Project-URL: Repository, https://github.com/class_sz_organization/hmfast
Project-URL: Documentation, https://hmfast.readthedocs.io
Keywords: halo model,cosmology,machine learning,jax,emulator
Classifier: Development Status :: 3 - Alpha
Classifier: Intended Audience :: Science/Research
Classifier: License :: OSI Approved :: MIT License
Classifier: Programming Language :: Python :: 3
Classifier: Programming Language :: Python :: 3.8
Classifier: Programming Language :: Python :: 3.9
Classifier: Programming Language :: Python :: 3.10
Classifier: Programming Language :: Python :: 3.11
Classifier: Topic :: Scientific/Engineering :: Astronomy
Classifier: Topic :: Scientific/Engineering :: Physics
Requires-Python: >=3.8
License-File: LICENSE
Requires-Dist: jax>=0.4.0
Requires-Dist: jaxlib>=0.4.0
Requires-Dist: numpy>=1.20.0
Requires-Dist: scipy>=1.7.0
Provides-Extra: dev
Requires-Dist: pytest>=6.0; extra == "dev"
Requires-Dist: pytest-cov; extra == "dev"
Requires-Dist: black; extra == "dev"
Requires-Dist: isort; extra == "dev"
Requires-Dist: flake8; extra == "dev"
Provides-Extra: docs
Requires-Dist: sphinx; extra == "docs"
Requires-Dist: sphinx-rtd-theme; extra == "docs"
Requires-Dist: numpydoc; extra == "docs"
Dynamic: license-file
